arxiv_db/__init__.py
arxiv_db/arxiv_dataclasses.py
arxiv_db/make.py
arxiv_db/models/Subscription_UniversalInstitution.py
arxiv_db/models/Subscription_UniversalInstitutionContact.py
arxiv_db/models/Subscription_UniversalInstitutionIP.py
arxiv_db/models/__init__.py
arxiv_db/models/admin_log.py
arxiv_db/models/admin_metadata.py
arxiv_db/models/archive_category.py
arxiv_db/models/archive_def.py
arxiv_db/models/archive_group.py
arxiv_db/models/archives.py
arxiv_db/models/arxiv_declarative.py
arxiv_db/models/associative_tables.py
arxiv_db/models/author_ids.py
arxiv_db/models/aws_config.py
arxiv_db/models/aws_files.py
arxiv_db/models/bib_feeds.py
arxiv_db/models/bib_updates.py
arxiv_db/models/bogus_countries.py
arxiv_db/models/categories.py
arxiv_db/models/category_def.py
arxiv_db/models/control_holds.py
arxiv_db/models/cross_control.py
arxiv_db/models/datacite_dois.py
arxiv_db/models/dbix_class_schema_versions.py
arxiv_db/models/dblp.py
arxiv_db/models/dblp_authors.py
arxiv_db/models/dblp_document_authors.py
arxiv_db/models/demographics.py
arxiv_db/models/document_category.py
arxiv_db/models/documents.py
arxiv_db/models/endorsement_domains.py
arxiv_db/models/endorsement_requests.py
arxiv_db/models/endorsement_requests_audit.py
arxiv_db/models/endorsements.py
arxiv_db/models/endorsements_audit.py
arxiv_db/models/freeze_log.py
arxiv_db/models/group_def.py
arxiv_db/models/groups.py
arxiv_db/models/jref_control.py
arxiv_db/models/licenses.py
arxiv_db/models/log_positions.py
arxiv_db/models/metadata.py
arxiv_db/models/mirror_list.py
arxiv_db/models/moderator_api_key.py
arxiv_db/models/monitor_klog.py
arxiv_db/models/monitor_mailq.py
arxiv_db/models/monitor_mailsent.py
arxiv_db/models/next_mail.py
arxiv_db/models/orcid_config.py
arxiv_db/models/orcid_ids.py
arxiv_db/models/ownership_requests.py
arxiv_db/models/ownership_requests_audit.py
arxiv_db/models/paper_owners.py
arxiv_db/models/paper_pw.py
arxiv_db/models/paper_sessions.py
arxiv_db/models/pilot_datasets.py
arxiv_db-0.12.0.dist-info/WHEEL
arxiv_db-0.12.0.dist-info/METADATA
arxiv_db-0.12.0.dist-info/RECORD
