Metadata-Version: 2.1
Name: arxiv-db
Version: 0.12.0
Summary: SQLAlchemy models for arXiv DB tables
Author: Brian D. Caruso
Author-email: bdc34@cornell.edu
Requires-Python: >=3.8,<4.0
Classifier: Programming Language :: Python :: 3
Classifier: Programming Language :: Python :: 3.8
Classifier: Programming Language :: Python :: 3.9
Classifier: Programming Language :: Python :: 3.10
Requires-Dist: sqlalchemy (>=1.4,<2.0)
